docker_cli/__init__.py
docker_cli-1.0.1.dist-info/WHEEL
docker_cli-1.0.1.dist-info/METADATA
docker_cli-1.0.1.dist-info/RECORD
