Metadata-Version: 2.1
Name: docker-cli
Version: 1.0.1
Summary: 
Author: Manu
Author-email: grajmanu@gmail.com
Requires-Python: >=3.6,<4.0
Classifier: Programming Language :: Python :: 3
Classifier: Programming Language :: Python :: 3.6
Classifier: Programming Language :: Python :: 3.7
Classifier: Programming Language :: Python :: 3.8
Classifier: Programming Language :: Python :: 3.9
Requires-Dist: Unidecode (>=1.2.0,<2.0.0)
Requires-Dist: clean-text (>=0.4.0,<0.5.0)
Requires-Dist: delegator.py (>=0.1.1,<0.2.0)
Requires-Dist: docker-compose (>=1.29.2,<2.0.0)
